mkdocs_labeled_user_defined_values/__init__.py
mkdocs_labeled_user_defined_values/plugin.py
mkdocs_labeled_user_defined_values-1.0.5.dist-info/LICENSE
mkdocs_labeled_user_defined_values-1.0.5.dist-info/METADATA
mkdocs_labeled_user_defined_values-1.0.5.dist-info/WHEEL
mkdocs_labeled_user_defined_values-1.0.5.dist-info/entry_points.txt
mkdocs_labeled_user_defined_values-1.0.5.dist-info/top_level.txt
mkdocs_labeled_user_defined_values-1.0.5.dist-info/RECORD
