Metadata-Version: 2.1
Name: mkdocs-labeled-user-defined-values
Version: 1.0.5
Summary: An enhanced version of mkdocs-user-defined-values. Keywords can now be categorized.
Home-page: https://github.com/amazerol/mkdocs-labeled-user-defined-values
Author: Alban MAZEROLLES
Project-URL: Bug Reports, https://github.com/amazerol/mkdocs-labeled-user-defined-values/issues
Project-URL: Source, https://github.com/amazerol/mkdocs-labeled-user-defined-values/
Keywords: mkdocs plugin multiple user defined value
Classifier: Intended Audience :: Developers
Classifier: Topic :: Software Development :: Build Tools
Classifier: License :: OSI Approved :: MIT License
Classifier: Programming Language :: Python :: 3
Classifier: Programming Language :: Python :: 3.5
Classifier: Programming Language :: Python :: 3.6
Classifier: Programming Language :: Python :: 3.7
Requires-Python: >=3, <4
License-File: LICENSE
Requires-Dist: mkdocs (==1.*)
Provides-Extra: dev
Requires-Dist: pipenv-setup ; extra == 'dev'
Requires-Dist: pylint ; extra == 'dev'
Requires-Dist: black ; extra == 'dev'
Requires-Dist: pytest ; extra == 'dev'
